{
  "main": {
    "id": "5324373015726ba8",
    "type": "split",
    "children": [
      {
        "id": "4509724f8bf84da7",
        "type": "tabs",
        "children": [
          {
            "id": "ad15acb6e9919011",
            "type": "leaf",
            "state": {
              "type": "markdown",
              "state": {
                "file": "Development/Алгоритмы и Структуры даных.md",
                "mode": "source",
                "source": false,
                "backlinks": true,
                "backlinkOpts": {
                  "collapseAll": false,
                  "extraContext": false,
                  "sortOrder": "alphabetical",
                  "showSearch": false,
                  "searchQuery": "",
                  "backlinkCollapsed": false,
                  "unlinkedCollapsed": true
                }
              },
              "icon": "lucide-file",
              "title": "Алгоритмы и Структуры даных"
            }
          },
          {
            "id": "ac014f84be876b5c",
            "type": "leaf",
            "state": {
              "type": "markdown",
              "state": {
                "file": "Soft/Agile/_lessons/Управление задачам.md",
                "mode": "source",
                "source": false,
                "backlinks": true,
                "backlinkOpts": {
                  "collapseAll": false,
                  "extraContext": false,
                  "sortOrder": "alphabetical",
                  "showSearch": false,
                  "searchQuery": "",
                  "backlinkCollapsed": false,
                  "unlinkedCollapsed": true
                }
              },
              "icon": "lucide-file",
              "title": "Управление задачам"
            }
          },
          {
            "id": "7c9701acc7feed5d",
            "type": "leaf",
            "state": {
              "type": "markdown",
              "state": {
                "file": "Development/DevOps/Kubernetes + Helm/_lessons/3. Знакомство с Kubernetes.md",
                "mode": "source",
                "source": false,
                "backlinks": true,
                "backlinkOpts": {
                  "collapseAll": false,
                  "extraContext": false,
                  "sortOrder": "alphabetical",
                  "showSearch": false,
                  "searchQuery": "",
                  "backlinkCollapsed": false,
                  "unlinkedCollapsed": true
                }
              },
              "icon": "lucide-file",
              "title": "3. Знакомство с Kubernetes"
            }
          },
          {
            "id": "a4a0a906fc76b769",
            "type": "leaf",
            "state": {
              "type": "markdown",
              "state": {
                "file": "Development/BackEnd/Microservices/_lessons/11. Консистентность данных.md",
                "mode": "source",
                "source": false,
                "backlinks": true,
                "backlinkOpts": {
                  "collapseAll": false,
                  "extraContext": false,
                  "sortOrder": "alphabetical",
                  "showSearch": false,
                  "searchQuery": "",
                  "backlinkCollapsed": false,
                  "unlinkedCollapsed": true
                }
              },
              "icon": "lucide-file",
              "title": "11. Консистентность данных"
            }
          },
          {
            "id": "8d85d6587cc9de68",
            "type": "leaf",
            "state": {
              "type": "markdown",
              "state": {
                "file": "Development/DevOps/Docker + Ansible/_lessons/10 Ansible playbooks.md",
                "mode": "source",
                "source": false,
                "backlinks": true,
                "backlinkOpts": {
                  "collapseAll": false,
                  "extraContext": false,
                  "sortOrder": "alphabetical",
                  "showSearch": false,
                  "searchQuery": "",
                  "backlinkCollapsed": false,
                  "unlinkedCollapsed": true
                }
              },
              "icon": "lucide-file",
              "title": "10 Ansible playbooks"
            }
          }
        ],
        "currentTab": 1
      }
    ],
    "direction": "vertical"
  },
  "left": {
    "id": "7d5d9729e93c69a0",
    "type": "split",
    "children": [
      {
        "id": "3a9f6fcffec95690",
        "type": "tabs",
        "children": [
          {
            "id": "48c5943284c71db8",
            "type": "leaf",
            "state": {
              "type": "file-explorer",
              "state": {
                "sortOrder": "alphabetical",
                "autoReveal": false
              },
              "icon": "lucide-folder-closed",
              "title": "Files"
            }
          },
          {
            "id": "c8a96e2fe293303a",
            "type": "leaf",
            "state": {
              "type": "search",
              "state": {
                "query": "DoR",
                "matchingCase": true,
                "explainSearch": false,
                "collapseAll": false,
                "extraContext": false,
                "sortOrder": "alphabetical"
              },
              "icon": "lucide-search",
              "title": "Search"
            }
          },
          {
            "id": "8a26a51640c36244",
            "type": "leaf",
            "state": {
              "type": "bookmarks",
              "state": {},
              "icon": "lucide-bookmark",
              "title": "Bookmarks"
            }
          },
          {
            "id": "d29b4086a66c80f5",
            "type": "leaf",
            "state": {
              "type": "recent-files",
              "state": {},
              "icon": "clock",
              "title": "Recent Files"
            }
          },
          {
            "id": "161c1394e2f60ce8",
            "type": "leaf",
            "state": {
              "type": "mk-path-view",
              "state": {},
              "icon": "layout-grid",
              "title": "Navigator"
            }
          }
        ],
        "currentTab": 4
      }
    ],
    "direction": "horizontal",
    "width": 305.5
  },
  "right": {
    "id": "5d906d621d61f331",
    "type": "split",
    "children": [
      {
        "id": "87f779e737b54d79",
        "type": "tabs",
        "dimension": 37.61792452830189,
        "children": [
          {
            "id": "55e165ebdb0aba10",
            "type": "leaf",
            "state": {
              "type": "backlink",
              "state": {
                "file": "Soft/Agile/_lessons/Масштабирование Agile.md",
                "collapseAll": false,
                "extraContext": false,
                "sortOrder": "alphabetical",
                "showSearch": false,
                "searchQuery": "",
                "backlinkCollapsed": false,
                "unlinkedCollapsed": true
              },
              "icon": "links-coming-in",
              "title": "Backlinks for Масштабирование Agile"
            }
          },
          {
            "id": "f2a11511413c62c1",
            "type": "leaf",
            "state": {
              "type": "outgoing-link",
              "state": {
                "file": "Soft/Agile/_lessons/Масштабирование Agile.md",
                "linksCollapsed": false,
                "unlinkedCollapsed": true
              },
              "icon": "links-going-out",
              "title": "Outgoing links from Масштабирование Agile"
            }
          },
          {
            "id": "912c743976f26aa3",
            "type": "leaf",
            "state": {
              "type": "tag",
              "state": {
                "sortOrder": "frequency",
                "useHierarchy": false,
                "showSearch": false,
                "searchQuery": ""
              },
              "icon": "lucide-tags",
              "title": "Tags"
            }
          },
          {
            "id": "6fa2dae8cc23e1d8",
            "type": "leaf",
            "state": {
              "type": "graph",
              "state": {},
              "icon": "lucide-git-fork",
              "title": "Graph view"
            }
          },
          {
            "id": "de42332dd051acc2",
            "type": "leaf",
            "state": {
              "type": "empty",
              "state": {},
              "icon": "lucide-file",
              "title": "New tab"
            }
          },
          {
            "id": "e34b07cb9f3f78d0",
            "type": "leaf",
            "state": {
              "type": "empty",
              "state": {},
              "icon": "lucide-file",
              "title": "New tab"
            }
          },
          {
            "id": "35609d7989f63c37",
            "type": "leaf",
            "state": {
              "type": "Saved Queries View",
              "state": {},
              "icon": "feather-mouse-pointer",
              "title": "Saved Queries"
            }
          },
          {
            "id": "db0b903b48f707c9",
            "type": "leaf",
            "state": {
              "type": "Saved Queries View",
              "state": {},
              "icon": "feather-mouse-pointer",
              "title": "Saved Queries"
            }
          }
        ],
        "currentTab": 7
      },
      {
        "id": "2df1decc2eef0b0b",
        "type": "tabs",
        "dimension": 62.382075471698116,
        "children": [
          {
            "id": "4d30a7c31882a75b",
            "type": "leaf",
            "state": {
              "type": "git-view",
              "state": {},
              "icon": "git-pull-request",
              "title": "Source Control"
            }
          },
          {
            "id": "656d24955483df37",
            "type": "leaf",
            "state": {
              "type": "outline",
              "state": {
                "file": "Soft/Agile/_lessons/Управление задачам.md",
                "followCursor": false,
                "showSearch": true,
                "searchQuery": ""
              },
              "icon": "lucide-list",
              "title": "Outline of Управление задачам"
            }
          }
        ],
        "currentTab": 1
      }
    ],
    "direction": "horizontal",
    "width": 257.5,
    "collapsed": true
  },
  "left-ribbon": {
    "hiddenItems": {
      "graph:Open graph view": false,
      "switcher:Open quick switcher": false,
      "canvas:Create new canvas": false,
      "daily-notes:Open today's daily note": false,
      "templates:Insert template": false,
      "command-palette:Open command palette": false,
      "workspaces:Manage workspace layouts": false,
      "table-editor-obsidian:Advanced Tables Toolbar": false,
      "obsidian-git:Open Git source control": false,
      "callout-manager:Insert Callout": false,
      "omnisearch:Omnisearch": false,
      "obsidian-excalidraw-plugin:New drawing": false,
      "obsidian-kanban:Create new board": false
    }
  },
  "active": "db0b903b48f707c9",
  "lastOpenFiles": [
    "Development/DevOps/Kubernetes + Helm/_lessons/3. Знакомство с Kubernetes.md",
    "Development/DevOps/Kubernetes + Helm/Kubernetes + Helm.md",
    "Development/DevOps/Kubernetes + Helm/_lessons/2. Настройка окружения.md",
    "Development/DevOps/Kubernetes + Helm/_lessons/1. Введение.md",
    "Soft/Agile/_lessons/Управление задачам.md",
    "Development/Алгоритмы и Структуры даных.md",
    "Development/DevOps/Docker + Ansible/_lessons/10 Ansible playbooks.md",
    "Development/BackEnd/Microservices/_lessons/11. Консистентность данных.md",
    "Development/DevOps/Kubernetes + Helm/_lessons/5. Работа с объектами.md",
    "Soft/Agile/_lessons/Scrum.md",
    "Development/BackEnd/Microservices/Паттерны и практика построения микросервисов.md",
    "Development/BackEnd/Microservices/_lessons/10. Реализация бизнес логики.md",
    "Development/BackEnd/Microservices/_lessons/9. Реализация API.md",
    "Development/BackEnd/Microservices/_lessons/8. Реализация взаимодействия.md",
    "Development/BackEnd/Microservices/_lessons/7. RabbitMQ.md",
    "Development/DevOps/Kubernetes + Helm/_lessons/4. Первый pod.md",
    "Development/DevOps/Kubernetes + Helm/_lessons/_png/Pasted image 20250622170338.png",
    "Development/DevOps/Kubernetes + Helm/_lessons/_png/Pasted image 20250622170107.png",
    "Development/DevOps/Kubernetes + Helm/_lessons/_png/Pasted image 20250622164927.png",
    "Development/DevOps/Kubernetes + Helm/_lessons/_png/Pasted image 20250622164853.png",
    "Development/DevOps/Kubernetes + Helm/_lessons/_png/Pasted image 20250622155305.png",
    "Development/DevOps/Kubernetes + Helm/_lessons/_png/Pasted image 20250622154540.png",
    "Development/DevOps/Kubernetes + Helm/_lessons/_png/Pasted image 20250622095427.png",
    "Development/DevOps/Kubernetes + Helm/_lessons/_png/Pasted image 20250622092936.png",
    "Environment/Aerospace.md",
    "Environment/_png/Screenshot 2025-06-21 at 14.37.22.png",
    "Environment/Terminal.md",
    "Environment/Yazi.md",
    "Environment/ZSH.md",
    "Environment/TMUX.md",
    "Environment/DataGrip.md",
    "Environment/WebStorm.md",
    "Environment",
    "Development/FrontEnd/State Managers/Zustand.md",
    "Development/Architecture/index.md",
    "Whats Learning/Прогресс изучения технологий.md",
    "Development/DevOps/Docker + Ansible/_lessons/_png/Pasted image 20250601195352.png",
    "Development/Testing/_png",
    "Development/Testing",
    "Development/DB/_png",
    "Development/Architecture/_png",
    "Development/DB",
    "_png",
    "Development/FrontEnd/Vue/_png",
    "Development/FrontEnd/Vue",
    "Development/FrontEnd/Angular"
  ]
}